agentic_commerce_protocol/__init__.py
agentic_commerce_protocol/models/__init__.py
agentic_commerce_protocol/models/address.py
agentic_commerce_protocol/models/allowance.py
agentic_commerce_protocol/models/allowance_reason.py
agentic_commerce_protocol/models/buyer.py
agentic_commerce_protocol/models/card_funding_type.py
agentic_commerce_protocol/models/card_number_type.py
agentic_commerce_protocol/models/check_performed_type.py
agentic_commerce_protocol/models/checkout_session.py
agentic_commerce_protocol/models/checkout_session_complete_request.py
agentic_commerce_protocol/models/checkout_session_create_request.py
agentic_commerce_protocol/models/checkout_session_status.py
agentic_commerce_protocol/models/checkout_session_update_request.py
agentic_commerce_protocol/models/common.py
agentic_commerce_protocol/models/content_type.py
agentic_commerce_protocol/models/delegate_payment_request.py
agentic_commerce_protocol/models/delegate_payment_response.py
agentic_commerce_protocol/models/error.py
agentic_commerce_protocol/models/error_code.py
agentic_commerce_protocol/models/error_type.py
agentic_commerce_protocol/models/event_data_order.py
agentic_commerce_protocol/models/fulfillment_option.py
agentic_commerce_protocol/models/fulfillment_option_digital.py
agentic_commerce_protocol/models/fulfillment_option_shipping.py
agentic_commerce_protocol/models/item.py
agentic_commerce_protocol/models/line_item.py
agentic_commerce_protocol/models/link.py
agentic_commerce_protocol/models/link_type.py
agentic_commerce_protocol/models/message.py
agentic_commerce_protocol/models/message_error.py
agentic_commerce_protocol/models/message_info.py
agentic_commerce_protocol/models/order.py
agentic_commerce_protocol/models/payment_data.py
agentic_commerce_protocol/models/payment_method_card.py
agentic_commerce_protocol/models/payment_method_type.py
agentic_commerce_protocol/models/payment_provider.py
agentic_commerce_protocol/models/payment_provider_type.py
agentic_commerce_protocol-0.2.0.dist-info/METADATA
agentic_commerce_protocol-0.2.0.dist-info/WHEEL
agentic_commerce_protocol-0.2.0.dist-info/top_level.txt
agentic_commerce_protocol-0.2.0.dist-info/RECORD
