Metadata-Version: 2.4
Name: agentic-commerce-protocol
Version: 0.2.0
Summary: Type definitions for the Agentic Commerce Protocol specification
Author: Svix
License: MIT
Project-URL: Homepage, https://github.com/svix/agentic-commerce-protocol
Project-URL: Documentation, https://developers.openai.com/commerce/guides/get-started
Project-URL: Repository, https://github.com/svix/agentic-commerce-protocol
Keywords: agentic-commerce,protocol,types,openai,stripe
Classifier: Development Status :: 3 - Alpha
Classifier: Intended Audience :: Developers
Classifier: License :: OSI Approved :: MIT License
Classifier: Programming Language :: Python :: 3
Classifier: Programming Language :: Python :: 3.9
Classifier: Programming Language :: Python :: 3.10
Classifier: Programming Language :: Python :: 3.11
Classifier: Programming Language :: Python :: 3.12
Requires-Python: >=3.9
Requires-Dist: pydantic>=2.11
